funkwhale_api_client/__init__.py
funkwhale_api_client/api/__init__.py
funkwhale_api_client/api/activity/__init__.py
funkwhale_api_client/api/activity/get_activity.py
funkwhale_api_client/api/albums/__init__.py
funkwhale_api_client/api/albums/create_album.py
funkwhale_api_client/api/albums/create_album_fetch.py
funkwhale_api_client/api/albums/create_album_mutation.py
funkwhale_api_client/api/albums/delete_album.py
funkwhale_api_client/api/albums/get_album.py
funkwhale_api_client/api/albums/get_album_fetches.py
funkwhale_api_client/api/albums/get_album_libraries.py
funkwhale_api_client/api/albums/get_album_mutations.py
funkwhale_api_client/api/albums/get_albums.py
funkwhale_api_client/api/artists/__init__.py
funkwhale_api_client/api/artists/create_artist_fetch.py
funkwhale_api_client/api/artists/create_artist_mutation.py
funkwhale_api_client/api/artists/get_artist.py
funkwhale_api_client/api/artists/get_artist_fetches.py
funkwhale_api_client/api/artists/get_artist_libraries.py
funkwhale_api_client/api/artists/get_artist_mutations.py
funkwhale_api_client/api/artists/get_artists.py
funkwhale_api_client/api/attachments/__init__.py
funkwhale_api_client/api/attachments/create_attachment.py
funkwhale_api_client/api/attachments/delete_attachment.py
funkwhale_api_client/api/attachments/get_attachment.py
funkwhale_api_client/api/attachments/get_attachment_proxy.py
funkwhale_api_client/api/auth/__init__.py
funkwhale_api_client/api/auth/change_password.py
funkwhale_api_client/api/auth/change_password_2.py
funkwhale_api_client/api/auth/confirm_password_reset.py
funkwhale_api_client/api/auth/get_auth_user.py
funkwhale_api_client/api/auth/partial_update_auth_user.py
funkwhale_api_client/api/auth/register.py
funkwhale_api_client/api/auth/reset_password.py
funkwhale_api_client/api/auth/update_auth_user.py
funkwhale_api_client/api/auth/verify_email.py
funkwhale_api_client/api/channels/__init__.py
funkwhale_api_client/api/channels/create_channel.py
funkwhale_api_client-0.1.1.dist-info/LICENSE
funkwhale_api_client-0.1.1.dist-info/WHEEL
funkwhale_api_client-0.1.1.dist-info/METADATA
funkwhale_api_client-0.1.1.dist-info/RECORD
